chinesevocablist/__init__.py
chinesevocablist/models.py
chinesevocablist/version.py
chinesevocablist/vocab_list_data.py
chinesevocablist-0.3.8.dist-info/LICENSE.md
chinesevocablist-0.3.8.dist-info/METADATA
chinesevocablist-0.3.8.dist-info/WHEEL
chinesevocablist-0.3.8.dist-info/top_level.txt
chinesevocablist-0.3.8.dist-info/RECORD
