Metadata-Version: 2.1
Name: chinesevocablist
Version: 0.3.8
Summary: Programmatic interface to the Chinese Vocab List
Home-page: http://github.com/kerrickstaley/Chinese-Vocab-List
Author: Kerrick Staley
Author-email: k@kerrickstaley.com
License: MIT
License-File: LICENSE.md
Requires-Dist: pyyaml >=3.12
